setup.cfg
setup.py
e2indicator/__init__.py
e2indicator/__main__.py
e2indicator/client.py
e2indicator/config.py
e2indicator/device.py
e2indicator/feedback.py
e2indicator/gtkupdater.py
e2indicator/indicator.py
e2indicator/mpris.py
e2indicator/state.py
e2indicator/streamscrobbler.py
e2indicator.egg-info/PKG-INFO
e2indicator.egg-info/SOURCES.txt
e2indicator.egg-info/dependency_links.txt
e2indicator.egg-info/entry_points.txt
e2indicator.egg-info/requires.txt
e2indicator.egg-info/top_level.txt