Metadata-Version: 1.1
Name: e2indicator
Version: 0.9.0
Summary: Ubuntu indicator for Enigma2
Home-page: https://github.com/aschaeffer/enigma2-indicator
Author: Andreas Schaeffer
Author-email: e2indicator@schaeffernet.de
License: GPLv3
Download-URL: https://github.com/aschaeffer/enigma2-indicator/archive/0.9.0.tar.gz
Keywords: enigma2,indicator,ubuntu,mpris
Platform: UNKNOWN
Classifier: Programming Language :: Python
Classifier: Programming Language :: Python :: 3
